paramiko_stat/__init__.py
paramiko_stat/client.py
paramiko_stat/sftp_client.py
paramiko_stat/transport.py
paramiko_stat-0.2.dist-info/LICENSE
paramiko_stat-0.2.dist-info/METADATA
paramiko_stat-0.2.dist-info/WHEEL
paramiko_stat-0.2.dist-info/top_level.txt
paramiko_stat-0.2.dist-info/RECORD
