Metadata-Version: 2.1
Name: paramiko-stat
Version: 0.2
Summary: Wrapper for paramiko with extra stat methods
Home-page: https://github.com/wbarnha/paramiko-stat/
Author: William Barnhart, Gordon P. Hemsley
License: UNKNOWN
Platform: UNKNOWN
License-File: LICENSE
Requires-Dist: paramiko
Provides-Extra: test
Requires-Dist: black ; extra == 'test'
Requires-Dist: coverage ; extra == 'test'
Requires-Dist: flake8 ; extra == 'test'
Requires-Dist: gitchangelog ; extra == 'test'
Requires-Dist: icecream ; extra == 'test'
Requires-Dist: isort ; extra == 'test'
Requires-Dist: mkdocs ; extra == 'test'
Requires-Dist: mypy ; extra == 'test'
Requires-Dist: pytest ; extra == 'test'
Requires-Dist: pytest-cov ; extra == 'test'
Requires-Dist: types-paramiko ; extra == 'test'
